license.txt
setup.py
sehha_learn/Binomialdistribution.py
sehha_learn/Gaussiandistribution.py
sehha_learn/Generaldistribution.py
sehha_learn/__init__.py
sehha_learn.egg-info/PKG-INFO
sehha_learn.egg-info/SOURCES.txt
sehha_learn.egg-info/dependency_links.txt
sehha_learn.egg-info/not-zip-safe
sehha_learn.egg-info/top_level.txt