Metadata-Version: 2.4
Name: sehha_learn
Version: 0.0.1
Summary: Sehha's learning package
Author: Abrar Mudhir
Author-email: abrar@sehha.io
License-File: license.txt
Dynamic: author
Dynamic: author-email
Dynamic: license-file
Dynamic: summary
